LICENSE.txt
README.rst
setup.py
petbenchmarks/Abstract.py
petbenchmarks/Distance.py
petbenchmarks/__init__.py
petbenchmarks/benchmarks.py
petbenchmarks/relationsextraction.py
petbenchmarks/tokenclassification.py
petbenchmarks.egg-info/PKG-INFO
petbenchmarks.egg-info/SOURCES.txt
petbenchmarks.egg-info/dependency_links.txt
petbenchmarks.egg-info/requires.txt
petbenchmarks.egg-info/top_level.txt