Metadata-Version: 2.1
Name: petbenchmarks
Version: 0.0.2
Summary: Benchmarking procedure to test Process Extraction from Text pproaches on the PET dataset
Home-page: https://pdi.fbk.eu/pet-dataset
Author: Patrizio Bellan
Author-email: patrizio.bellan@gmail.com
Maintainer: Patrizio Bellan
Maintainer-email: patrizio.bellan@gmail.com
License: MIT
Keywords: huggingface,PET,dataset,benchmark,process extraction from text,natural language processing,nlp,business process management,bpm
Platform: Any
Classifier: Development Status :: 3 - Alpha
Classifier: License :: OSI Approved :: MIT License
Classifier: Natural Language :: English
Classifier: Intended Audience :: Science/Research
Classifier: Intended Audience :: Developers
Classifier: Intended Audience :: Education
Classifier: Intended Audience :: End Users/Desktop
Classifier: Intended Audience :: Information Technology
Classifier: Programming Language :: Python :: 3
Classifier: Programming Language :: Python :: 3.5
Classifier: Programming Language :: Python :: 3.6
Classifier: Programming Language :: Python :: 3.7
Classifier: Programming Language :: Python :: 3.8
Classifier: Programming Language :: Python :: 3.9
Classifier: Programming Language :: Python :: 3.10
Classifier: Programming Language :: Python :: 3.11
Classifier: Programming Language :: Python :: 3.12
Classifier: Topic :: Scientific/Engineering
Classifier: Topic :: Utilities
Requires-Python: !=2.7, >=3.5.*
License-File: LICENSE.txt
